CODEOWNERS
LICENSE
MANIFEST.in
README.md
setup.py
Semi_ATE/__init__.py
Semi_ATE/STIL/__init__.py
Semi_ATE/STIL/lsp/ExtractAST.py
Semi_ATE/STIL/lsp/VACounter.py
Semi_ATE/STIL/lsp/__init__.py
Semi_ATE/STIL/parsers/DomainUtils.py
Semi_ATE/STIL/parsers/HashInfo.py
Semi_ATE/STIL/parsers/HeaderBlockParser.py
Semi_ATE/STIL/parsers/MacroDefsBlockParser.py
Semi_ATE/STIL/parsers/PattVecCmd.py
Semi_ATE/STIL/parsers/PatternBlockParser.py
Semi_ATE/STIL/parsers/PatternBurstBlockParser.py
Semi_ATE/STIL/parsers/PatternExecBlockParser.py
Semi_ATE/STIL/parsers/ProceduresBlockParser.py
Semi_ATE/STIL/parsers/STILBlockParser.py
Semi_ATE/STIL/parsers/STILDumpCompiler.py
Semi_ATE/STIL/parsers/STILDumpCompilerExceptions.py
Semi_ATE/STIL/parsers/STILLark.py
Semi_ATE/STIL/parsers/STILParser.py
Semi_ATE/STIL/parsers/STILSemanticException.py
Semi_ATE/STIL/parsers/ScanStructBlockParser.py
Semi_ATE/STIL/parsers/SelectorBlockParser.py
Semi_ATE/STIL/parsers/SigTimingInfo.py
Semi_ATE/STIL/parsers/SignalGroupsBlockParser.py
Semi_ATE/STIL/parsers/SignalsBlockParser.py
Semi_ATE/STIL/parsers/SpecBlockParser.py
Semi_ATE/STIL/parsers/SyntaxParserExceptions.py
Semi_ATE/STIL/parsers/TimeUtils.py
Semi_ATE/STIL/parsers/TimingBlockParser.py
Semi_ATE/STIL/parsers/WFCUtils.py
Semi_ATE/STIL/parsers/__init__.py
Semi_ATE/STIL/parsers/utils.py
Semi_ATE/STIL/parsers/grammars/b_header.lark
Semi_ATE/STIL/parsers/grammars/b_macrodefs.lark
Semi_ATE/STIL/parsers/grammars/b_pattern.lark
Semi_ATE/STIL/parsers/grammars/b_pattern_burst.lark
Semi_ATE/STIL/parsers/grammars/b_pattern_exec.lark
Semi_ATE/STIL/parsers/grammars/b_procedures.lark
Semi_ATE/STIL/parsers/grammars/b_scan_structures.lark
Semi_ATE/STIL/parsers/grammars/b_selector.lark
Semi_ATE/STIL/parsers/grammars/b_signal_groups.lark
Semi_ATE/STIL/parsers/grammars/b_signals.lark
Semi_ATE/STIL/parsers/grammars/b_spec.lark
Semi_ATE/STIL/parsers/grammars/b_stil.lark
Semi_ATE/STIL/parsers/grammars/b_timing.lark
Semi_ATE/STIL/parsers/grammars/base.lark
Semi_ATE_STIL.egg-info/PKG-INFO
Semi_ATE_STIL.egg-info/SOURCES.txt
Semi_ATE_STIL.egg-info/dependency_links.txt
Semi_ATE_STIL.egg-info/top_level.txt
